MANIFEST.in
README.rst
setup.py
c/Makefile
c/fastpbkdf2/.travis.yml
c/fastpbkdf2/LICENSE
c/fastpbkdf2/Makefile
c/fastpbkdf2/Makefile.nmake
c/fastpbkdf2/README.md
c/fastpbkdf2/WINDOWS.md
c/fastpbkdf2/bench.c
c/fastpbkdf2/benchmulti.c
c/fastpbkdf2/benchutil.h
c/fastpbkdf2/fastpbkdf2.c
c/fastpbkdf2/fastpbkdf2.h
c/fastpbkdf2/gentests.py
c/fastpbkdf2/testdata.py
c/fastpbkdf2/testfastpbkdf2.c
c/py-bcrypt/LICENSE
c/py-bcrypt/MANIFEST.in
c/py-bcrypt/PKG-INFO
c/py-bcrypt/README
c/py-bcrypt/TODO
c/py-bcrypt/setup.py
c/py-bcrypt/bcrypt/__init__.py
c/py-bcrypt/bcrypt/bcrypt.c
c/py-bcrypt/bcrypt/bcrypt_pbkdf.c
c/py-bcrypt/bcrypt/bcrypt_python.c
c/py-bcrypt/bcrypt/blowfish.c
c/py-bcrypt/bcrypt/pybc_blf.h
c/py-bcrypt/bcrypt/pybc_sha2.h
c/py-bcrypt/bcrypt/sha2.c
c/py-bcrypt/bcrypt/timingsafe_bcmp.c
c/py-bcrypt/test/test.py
c/scrypt/.autom4te.cfg
c/scrypt/.travis.yml
c/scrypt/BSDmakefile
c/scrypt/FORMAT
c/scrypt/Makefile.am
c/scrypt/README.md
c/scrypt/config_freebsd.h
c/scrypt/configure.ac
c/scrypt/main.c
c/scrypt/scrypt-version
c/scrypt/scrypt.1
c/scrypt/scrypt_platform.h
c/scrypt/lib/README
c/scrypt/lib/crypto/crypto_scrypt-ref.c
c/scrypt/lib/crypto/crypto_scrypt.c
c/scrypt/lib/crypto/crypto_scrypt.h
c/scrypt/lib/crypto/crypto_scrypt_smix.c
c/scrypt/lib/crypto/crypto_scrypt_smix.h
c/scrypt/lib/crypto/crypto_scrypt_smix_sse2.c
c/scrypt/lib/crypto/crypto_scrypt_smix_sse2.h
c/scrypt/lib/scryptenc/scryptenc.c
c/scrypt/lib/scryptenc/scryptenc.h
c/scrypt/lib/scryptenc/scryptenc_cpuperf.c
c/scrypt/lib/scryptenc/scryptenc_cpuperf.h
c/scrypt/lib/util/memlimit.c
c/scrypt/lib/util/memlimit.h
c/scrypt/libcperciva/COPYRIGHT
c/scrypt/libcperciva/alg/sha256.c
c/scrypt/libcperciva/alg/sha256.h
c/scrypt/libcperciva/cpusupport/cpusupport.h
c/scrypt/libcperciva/cpusupport/cpusupport_x86_aesni.c
c/scrypt/libcperciva/cpusupport/cpusupport_x86_sse2.c
c/scrypt/libcperciva/cpusupport/Build/cpusupport-X86-AESNI.c
c/scrypt/libcperciva/cpusupport/Build/cpusupport-X86-CPUID.c
multikdf.egg-info/PKG-INFO
multikdf.egg-info/SOURCES.txt
multikdf.egg-info/dependency_links.txt
multikdf.egg-info/requires.txt
multikdf.egg-info/top_level.txt
multikdf.egg-info/zip-safe
