Metadata-Version: 1.1
Name: multikdf
Version: 0.01.32
Summary: multikdf
Home-page: https://github.com/sundarnagarajan/pymultikdf
Author: Sundar Nagarajan
Author-email: UNKNOWN
License: License :: OSI Approved :: GNU Lesser General Public License v3 or later (LGPLv3+)
Download-URL: https://github.com/sundarnagarajan/pymultikdf/tree/0.01.32
Platform: UNKNOWN
Classifier: Development Status :: 4 - Beta
Classifier: Programming Language :: Python :: 2
Classifier: Programming Language :: Python :: 3
Classifier: Programming Language :: Python :: Implementation :: PyPy
Classifier: License :: OSI Approved :: MIT License
Classifier: License :: OSI Approved :: GNU Lesser General Public License v3 or later (LGPLv3+)
